ccip_sdk/__init__.py
ccip_sdk/client.py
ccip_sdk/configs.py
ccip_sdk/utils.py
ccip_sdk/ccip_directory/data.json
ccip_sdk/contracts/artifacts/contracts/CCIPContract/CCIPContract.json
ccip_sdk-0.1.127.dist-info/licenses/LICENSE
ccip_sdk-0.1.127.dist-info/METADATA
ccip_sdk-0.1.127.dist-info/WHEEL
ccip_sdk-0.1.127.dist-info/top_level.txt
ccip_sdk-0.1.127.dist-info/RECORD
