Metadata-Version: 2.4
Name: ccip-sdk
Version: 0.1.127
Summary: The simplest Python SDK for Chainlink CCIP that turns complex cross-chain operations into 15 lines of code.
Home-page: https://github.com/dhananjaypai08/ccip-sdk
Author: Dhananjay Pai
Author-email: dhananjay2002pai@gmail.com
License: MIT
Classifier: Programming Language :: Python :: 3
Classifier: License :: OSI Approved :: MIT License
Classifier: Development Status :: 3 - Alpha
Classifier: Intended Audience :: Developers
Classifier: Operating System :: OS Independent
Requires-Python: >=3.8
License-File: LICENSE
Requires-Dist: web3
Requires-Dist: eth_account
Requires-Dist: requests
Dynamic: author
Dynamic: author-email
Dynamic: classifier
Dynamic: description
Dynamic: description-content-type
Dynamic: home-page
Dynamic: license
Dynamic: license-file
Dynamic: requires-dist
Dynamic: requires-python
Dynamic: summary
